{
    "key": "group_5ea055a02df03",
    "title": "FormCareModal:info",
    "fields": [
        {
            "key": "field_5ea055c1fde18",
            "label": "Title",
            "name": "title",
            "type": "text",
            "instructions": "",
            "required": 1,
            "conditional_logic": 0,
            "wrapper": {
                "width": "",
                "class": "",
                "id": ""
            },
            "show_in_graphql": 1,
            "default_value": "Please fill out the form to get Alzheimer's and dementia care information:",
            "placeholder": "Form title text",
            "prepend": "",
            "append": "",
            "maxlength": ""
        },
        {
            "key": "field_5ea05645fde19",
            "label": "Close Text",
            "name": "close_text",
            "type": "text",
            "instructions": "Copy for the close button",
            "required": 0,
            "conditional_logic": 0,
            "wrapper": {
                "width": "",
                "class": "",
                "id": ""
            },
            "show_in_graphql": 1,
            "default_value": "x",
            "placeholder": "x",
            "prepend": "",
            "append": "",
            "maxlength": ""
        },
        {
            "key": "field_5ea05f9cfde1b",
            "label": "Input Fields",
            "name": "input_fields",
            "type": "repeater",
            "instructions": "",
            "required": 0,
            "conditional_logic": 0,
            "wrapper": {
                "width": "",
                "class": "",
                "id": ""
            },
            "show_in_graphql": 1,
            "collapsed": "",
            "min": 0,
            "max": 0,
            "layout": "table",
            "button_label": "",
            "sub_fields": [
                {
                    "key": "field_5ea05fc8fde1c",
                    "label": "Label",
                    "name": "label",
                    "type": "text",
                    "instructions": "",
                    "required": 1,
                    "conditional_logic": 0,
                    "wrapper": {
                        "width": "",
                        "class": "",
                        "id": ""
                    },
                    "show_in_graphql": 1,
                    "default_value": "",
                    "placeholder": "",
                    "prepend": "",
                    "append": "",
                    "maxlength": ""
                },
                {
                    "key": "field_5ea06021fde1d",
                    "label": "Placeholder",
                    "name": "placeholder",
                    "type": "text",
                    "instructions": "",
                    "required": 0,
                    "conditional_logic": 0,
                    "wrapper": {
                        "width": "",
                        "class": "",
                        "id": ""
                    },
                    "show_in_graphql": 1,
                    "default_value": "",
                    "placeholder": "",
                    "prepend": "",
                    "append": "",
                    "maxlength": ""
                },
                {
                    "key": "field_5ea8e2dd8b892",
                    "label": "Helper Text",
                    "name": "helper_text",
                    "type": "text",
                    "instructions": "Text displayed if field doesn't validate to help the user fix the input.",
                    "required": 1,
                    "conditional_logic": 0,
                    "wrapper": {
                        "width": "",
                        "class": "",
                        "id": ""
                    },
                    "show_in_graphql": 1,
                    "default_value": "",
                    "placeholder": "",
                    "prepend": "",
                    "append": "",
                    "maxlength": ""
                },
                {
                    "key": "field_5ea06038fde1e",
                    "label": "Required",
                    "name": "required",
                    "type": "true_false",
                    "instructions": "",
                    "required": 0,
                    "conditional_logic": 0,
                    "wrapper": {
                        "width": "",
                        "class": "",
                        "id": ""
                    },
                    "show_in_graphql": 1,
                    "message": "",
                    "default_value": 0,
                    "ui": 0,
                    "ui_on_text": "",
                    "ui_off_text": ""
                }
            ]
        },
        {
            "key": "field_5ea06307ef93a",
            "label": "Submit Text",
            "name": "submit_text",
            "type": "text",
            "instructions": "Submit button text",
            "required": 0,
            "conditional_logic": 0,
            "wrapper": {
                "width": "",
                "class": "",
                "id": ""
            },
            "show_in_graphql": 1,
            "default_value": "Request Info",
            "placeholder": "Request Info",
            "prepend": "",
            "append": "",
            "maxlength": ""
        },
        {
            "key": "field_5ea05f2ffde1a",
            "label": "Legal Text",
            "name": "legal_text",
            "type": "textarea",
            "instructions": "Legal language for the form footer. Use {{ template }} format for any links.",
            "required": 0,
            "conditional_logic": 0,
            "wrapper": {
                "width": "",
                "class": "",
                "id": ""
            },
            "show_in_graphql": 1,
            "default_value": "",
            "placeholder": "",
            "maxlength": "",
            "rows": "",
            "new_lines": ""
        }
    ],
    "location": [
        [
            {
                "param": "post",
                "operator": "==",
                "value": "88927"
            }
        ],
        [
            {
                "param": "slug",
                "operator": "==",
                "value": "form-care-modal-feature"
            }
        ]
    ],
    "menu_order": 0,
    "position": "normal",
    "style": "default",
    "label_placement": "top",
    "instruction_placement": "label",
    "hide_on_screen": "",
    "active": 1,
    "description": "",
    "show_in_graphql": 1,
    "graphql_field_name": "FormCareModal",
    "modified": 1588266406
}